{"Compostela Valley":"\/Mindanao\/Davao_Region\/Compostela_Valley\/","Compostela, Compostela Valley":"\/Mindanao\/Davao_Region\/Compostela_Valley\/Compostela\/","Laak (San Vicente), Compostela Valley":"\/Mindanao\/Davao_Region\/Compostela_Valley\/Laak\/","Mabini (Do\u00f1a Alicia), Compostela Valley":"\/Mindanao\/Davao_Region\/Compostela_Valley\/Mabini\/","Maco, Compostela Valley":"\/Mindanao\/Davao_Region\/Compostela_Valley\/Maco\/","Maragusan (San Mariano), Compostela Valley":"\/Mindanao\/Davao_Region\/Compostela_Valley\/Maragusan\/","Mawab, Compostela Valley":"\/Mindanao\/Davao_Region\/Compostela_Valley\/Mawab\/","Monkayo, Compostela Valley":"\/Mindanao\/Davao_Region\/Compostela_Valley\/Monkayo\/","Montevista, Compostela Valley":"\/Mindanao\/Davao_Region\/Compostela_Valley\/Montevista\/","Nabunturan, Compostela Valley":"\/Mindanao\/Davao_Region\/Compostela_Valley\/Nabunturan\/","New Bataan, Compostela Valley":"\/Mindanao\/Davao_Region\/Compostela_Valley\/New_Bataan\/","Pantukan, Compostela Valley":"\/Mindanao\/Davao_Region\/Compostela_Valley\/Pantukan\/","Davao (Davao Del Norte)":"\/Mindanao\/Davao_Region\/Davao\/","Asuncion (Saug), Davao (Davao Del Norte)":"\/Mindanao\/Davao_Region\/Davao\/Asuncion\/","Braulio E. Dujali, Davao (Davao Del Norte)":"\/Mindanao\/Davao_Region\/Davao\/Braulio_E._Dujali\/","Carmen, Davao (Davao Del Norte)":"\/Mindanao\/Davao_Region\/Davao\/Carmen\/","City Of Tagum, Davao (Davao Del Norte)":"\/Mindanao\/Davao_Region\/Davao\/City_Of_Tagum\/","Island Garden City Of Samal, Davao (Davao Del Norte)":"\/Mindanao\/Davao_Region\/Davao\/Island_Garden_City_Of_Samal\/","Kapalong, Davao (Davao Del Norte)":"\/Mindanao\/Davao_Region\/Davao\/Kapalong\/","New Corella, Davao (Davao Del Norte)":"\/Mindanao\/Davao_Region\/Davao\/New_Corella\/","Panabo City, Davao (Davao Del Norte)":"\/Mindanao\/Davao_Region\/Davao\/Panabo_City\/","San Isidro, Davao (Davao Del Norte)":"\/Mindanao\/Davao_Region\/Davao\/San_Isidro\/","Santo Tomas, Davao (Davao Del Norte)":"\/Mindanao\/Davao_Region\/Davao\/Santo_Tomas\/","Talaingod, Davao (Davao Del Norte)":"\/Mindanao\/Davao_Region\/Davao\/Talaingod\/","Davao Del Sur":"\/Mindanao\/Davao_Region\/Davao_Del_Sur\/","Bansalan, Davao Del Sur":"\/Mindanao\/Davao_Region\/Davao_Del_Sur\/Bansalan\/","Davao City, Davao Del Sur":"\/Mindanao\/Davao_Region\/Davao_Del_Sur\/Davao_City\/","Digos City, Davao Del Sur":"\/Mindanao\/Davao_Region\/Davao_Del_Sur\/Digos_City\/","Hagonoy, Davao Del Sur":"\/Mindanao\/Davao_Region\/Davao_Del_Sur\/Hagonoy\/","Kiblawan, Davao Del Sur":"\/Mindanao\/Davao_Region\/Davao_Del_Sur\/Kiblawan\/","Magsaysay, Davao Del Sur":"\/Mindanao\/Davao_Region\/Davao_Del_Sur\/Magsaysay\/","Malalag, Davao Del Sur":"\/Mindanao\/Davao_Region\/Davao_Del_Sur\/Malalag\/","Matanao, Davao Del Sur":"\/Mindanao\/Davao_Region\/Davao_Del_Sur\/Matanao\/","Padada, Davao Del Sur":"\/Mindanao\/Davao_Region\/Davao_Del_Sur\/Padada\/","Santa Cruz, Davao Del Sur":"\/Mindanao\/Davao_Region\/Davao_Del_Sur\/Santa_Cruz\/","Sulop, Davao Del Sur":"\/Mindanao\/Davao_Region\/Davao_Del_Sur\/Sulop\/","Davao Occidental":"\/Mindanao\/Davao_Region\/Davao_Occidental\/","Don Marcelino, Davao Occidental":"\/Mindanao\/Davao_Region\/Davao_Occidental\/Don_Marcelino\/","Jose Abad Santos (Trinidad), Davao Occidental":"\/Mindanao\/Davao_Region\/Davao_Occidental\/Jose_Abad_Santos\/","Malita, Davao Occidental":"\/Mindanao\/Davao_Region\/Davao_Occidental\/Malita\/","Santa Maria, Davao Occidental":"\/Mindanao\/Davao_Region\/Davao_Occidental\/Santa_Maria\/","Sarangani, Davao Occidental":"\/Mindanao\/Davao_Region\/Davao_Occidental\/Sarangani\/","Davao Oriental":"\/Mindanao\/Davao_Region\/Davao_Oriental\/","Baganga, Davao Oriental":"\/Mindanao\/Davao_Region\/Davao_Oriental\/Baganga\/","Banaybanay, Davao Oriental":"\/Mindanao\/Davao_Region\/Davao_Oriental\/Banaybanay\/","Boston, Davao Oriental":"\/Mindanao\/Davao_Region\/Davao_Oriental\/Boston\/","Caraga, Davao Oriental":"\/Mindanao\/Davao_Region\/Davao_Oriental\/Caraga\/","Cateel, Davao Oriental":"\/Mindanao\/Davao_Region\/Davao_Oriental\/Cateel\/","Governor Generoso, Davao Oriental":"\/Mindanao\/Davao_Region\/Davao_Oriental\/Governor_Generoso\/","Lupon, Davao Oriental":"\/Mindanao\/Davao_Region\/Davao_Oriental\/Lupon\/","Manay, Davao Oriental":"\/Mindanao\/Davao_Region\/Davao_Oriental\/Manay\/","Mati City, Davao Oriental":"\/Mindanao\/Davao_Region\/Davao_Oriental\/Mati_City\/","San Isidro, Davao Oriental":"\/Mindanao\/Davao_Region\/Davao_Oriental\/San_Isidro\/","Tarragona, Davao Oriental":"\/Mindanao\/Davao_Region\/Davao_Oriental\/Tarragona\/"}