{"Alubijid":"\/Mindanao\/Northern_Mindanao\/Misamis_Oriental\/Alubijid\/","Balingasag":"\/Mindanao\/Northern_Mindanao\/Misamis_Oriental\/Balingasag\/","Balingoan":"\/Mindanao\/Northern_Mindanao\/Misamis_Oriental\/Balingoan\/","Binuangan":"\/Mindanao\/Northern_Mindanao\/Misamis_Oriental\/Binuangan\/","Cagayan De Oro City":"\/Mindanao\/Northern_Mindanao\/Misamis_Oriental\/Cagayan_De_Oro_City\/","Claveria":"\/Mindanao\/Northern_Mindanao\/Misamis_Oriental\/Claveria\/","El Salvador City":"\/Mindanao\/Northern_Mindanao\/Misamis_Oriental\/El_Salvador_City\/","Gingoog City":"\/Mindanao\/Northern_Mindanao\/Misamis_Oriental\/Gingoog_City\/","Gitagum":"\/Mindanao\/Northern_Mindanao\/Misamis_Oriental\/Gitagum\/","Initao":"\/Mindanao\/Northern_Mindanao\/Misamis_Oriental\/Initao\/","Jasaan":"\/Mindanao\/Northern_Mindanao\/Misamis_Oriental\/Jasaan\/","Kinoguitan":"\/Mindanao\/Northern_Mindanao\/Misamis_Oriental\/Kinoguitan\/","Lagonglong":"\/Mindanao\/Northern_Mindanao\/Misamis_Oriental\/Lagonglong\/","Laguindingan":"\/Mindanao\/Northern_Mindanao\/Misamis_Oriental\/Laguindingan\/","Libertad":"\/Mindanao\/Northern_Mindanao\/Misamis_Oriental\/Libertad\/","Lugait":"\/Mindanao\/Northern_Mindanao\/Misamis_Oriental\/Lugait\/","Magsaysay (Linugos)":"\/Mindanao\/Northern_Mindanao\/Misamis_Oriental\/Magsaysay\/","Manticao":"\/Mindanao\/Northern_Mindanao\/Misamis_Oriental\/Manticao\/","Medina":"\/Mindanao\/Northern_Mindanao\/Misamis_Oriental\/Medina\/","Naawan":"\/Mindanao\/Northern_Mindanao\/Misamis_Oriental\/Naawan\/","Opol":"\/Mindanao\/Northern_Mindanao\/Misamis_Oriental\/Opol\/","Salay":"\/Mindanao\/Northern_Mindanao\/Misamis_Oriental\/Salay\/","Sugbongcogon":"\/Mindanao\/Northern_Mindanao\/Misamis_Oriental\/Sugbongcogon\/","Tagoloan":"\/Mindanao\/Northern_Mindanao\/Misamis_Oriental\/Tagoloan\/","Talisayan":"\/Mindanao\/Northern_Mindanao\/Misamis_Oriental\/Talisayan\/","Villanueva":"\/Mindanao\/Northern_Mindanao\/Misamis_Oriental\/Villanueva\/"}